{
    "dataset": "Cora",
    "task": "LP",
    "root_path": "D:\\datasets\\Graphs",
    "batch_size": 300,
    "eval_freq": 100,
    "exp_iters": 5,
    "version": "run",
    "log_path": "./results/v2302152230/cls_Cora.log",
    "pre_epochs": 200,
    "epochs": 1000,
    "height": 3,
    "lr_pre": 0.01,
    "lr": 0.001,
    "w_decay": 0.0,
    "decay_rate": null,
    "max_nums": [
        50,
        7
    ],
    "embed_dim": 2,
    "hidden_dim_enc": 32,
    "hidden_dim": 32,
    "dropout": 0.4,
    "nonlin": null,
    "temperature": 0.05,
    "n_cluster_trials": 5,
    "t": 1.0,
    "r": 2.0,
    "patience": 5,
    "save_path": "model.pt",
    "use_gpu": true,
    "gpu": 0,
    "devices": "0,1"
}